firstpackie.py
firstpackie-1.0.0.dist-info/LICENSE
firstpackie-1.0.0.dist-info/METADATA
firstpackie-1.0.0.dist-info/WHEEL
firstpackie-1.0.0.dist-info/top_level.txt
firstpackie-1.0.0.dist-info/RECORD
