Metadata-Version: 2.1
Name: firstpackie
Version: 1.0.0
Summary: Say hello!
Home-page: https://github.com/taslim-a-hussain/firstpackie
Author: Taslim A Hussain
Author-email: taslim@outlook.co.nz
License: UNKNOWN
Platform: UNKNOWN
Classifier: Programming Language :: Python :: 3
Classifier: Programming Language :: Python :: 3.3
Classifier: Programming Language :: Python :: 3.6
Classifier: Programming Language :: Python :: 3.7
Classifier: License :: OSI Approved :: GNU General Public License v3 (GPLv3)
Classifier: Operating System :: OS Independent
License-File: LICENSE
